{
  "title": "Mass Effect Franchise",
  "platform": "PC",
  "type": "video",
  "description": "I'm Commander Shephard, and this is the best game on the Citadel. The Mass Effect series redefined what a narrative-driven RPG could be, with its deep character relationships, meaningful choices, and a universe that feels truly alive.",
  "imageUrl": "https://image.api.playstation.com/vulcan/img/rnd/202010/2621/2QaKvJVWvzF7N0UfD3ebiO2k.png",
  "slug": "mass-effect-franchise",
  "createdAt": "2025-05-29T03:59:14.172Z",
  "updatedAt": "2025-05-29T03:59:14.178Z"
}
